MANIFEST.in
README.rst
requirements.txt
setup.py
test_requirements.txt
auction/__init__.py
auction/admin.py
auction/context_processors.py
auction/forms.py
auction/urls.py
auction/views.py
auction/migrations/0001_initial.py
auction/migrations/0002_auto__del_field_biditem_lot__add_field_biditem_lot_id.py
auction/migrations/0003_auto__add_field_biditem_content_type.py
auction/migrations/__init__.py
auction/models/__init__.py
auction/models/auctionmodel.py
auction/models/bases.py
auction/models/bidbasket.py
auction/models/biditem.py
auction/models/defaults.py
auction/models/lot.py
auction/templates/auction/auctions.html
auction/templates/auction/base.html
auction/templates/auction/bids.html
auction/templates/auction/lot.html
auction/templates/auction/lots.html
auction/tests/__init__.py
auction/tests/runtests.py
auction/tests/test_models.py
auction/tests/urls.py
auction/tests/coverage/errors.html
auction/tests/coverage/excludes.html
auction/tests/coverage/index.html
auction/tests/coverage/modules/auction.__init__.html
auction/tests/coverage/modules/auction.context_processors.html
auction/tests/coverage/modules/auction.forms.html
auction/tests/coverage/modules/auction.models.__init__.html
auction/tests/coverage/modules/auction.models.auctionmodel.html
auction/tests/coverage/modules/auction.models.bases.html
auction/tests/coverage/modules/auction.models.bidbasket.html
auction/tests/coverage/modules/auction.models.biditem.html
auction/tests/coverage/modules/auction.models.defaults.html
auction/tests/coverage/modules/auction.models.lot.html
auction/tests/coverage/modules/auction.utils.generic.html
auction/tests/coverage/modules/auction.utils.loader.html
auction/utils/__init__.py
auction/utils/generic.py
auction/utils/loader.py
django_auction.egg-info/PKG-INFO
django_auction.egg-info/SOURCES.txt
django_auction.egg-info/dependency_links.txt
django_auction.egg-info/not-zip-safe
django_auction.egg-info/requires.txt
django_auction.egg-info/top_level.txt